nima_cast/__init__.py
nima_cast/nima_cast_cmd.py
nima_cast-0.1.12.dist-info/LICENSE
nima_cast-0.1.12.dist-info/METADATA
nima_cast-0.1.12.dist-info/WHEEL
nima_cast-0.1.12.dist-info/entry_points.txt
nima_cast-0.1.12.dist-info/top_level.txt
nima_cast-0.1.12.dist-info/RECORD
