Metadata-Version: 2.1
Name: nima-cast
Version: 0.1.12
Summary: This is a project that could connect to a minio server and sream the conents on a chromecast device.
Home-page: https://github.com/nimamahmoudi/nima_cast
Author: Nima Mahmoudi
Author-email: nima_mahmoudi@live.com
License: UNKNOWN
Platform: UNKNOWN
Classifier: Development Status :: 3 - Alpha
Classifier: Programming Language :: Python
Classifier: Programming Language :: Python :: 3
Classifier: Programming Language :: Python :: 3.6
Classifier: Intended Audience :: Developers
Classifier: License :: OSI Approved :: MIT License
Classifier: Operating System :: OS Independent
Requires-Dist: minio
Requires-Dist: PyChromecast (>=3.2.2)
